quakesranalysis/__init__.py
quakesranalysis/allan.py
quakesranalysis/gaussianmixture.py
quakesranalysis/mixturefit.py
quakesranalysis/scanhandler.py
quakesranalysis/utils/__init__.py
quakesranalysis/utils/util_fetchruns.py
quakesranalysis/utils/util_slicescan.py
quakesranalysis/utils/util_standardplots.py
quakesranalysis_tspspi-0.0.9.dist-info/LICENSE.md
quakesranalysis_tspspi-0.0.9.dist-info/METADATA
quakesranalysis_tspspi-0.0.9.dist-info/WHEEL
quakesranalysis_tspspi-0.0.9.dist-info/entry_points.txt
quakesranalysis_tspspi-0.0.9.dist-info/top_level.txt
quakesranalysis_tspspi-0.0.9.dist-info/RECORD
