Metadata-Version: 2.1
Name: quakesranalysis-tspspi
Version: 0.0.9
Summary: Analysis package for QUAK/ESR runs
Home-page: https://github.com/tspspi/quakesranalysis
Author: Thomas Spielauer
Author-email: pypipackages01@tspi.at
Classifier: Programming Language :: Python :: 3
Classifier: License :: OSI Approved :: BSD License
Classifier: Operating System :: OS Independent
Requires-Python: >=3.6
License-File: LICENSE.md
Requires-Dist: numpy (>=1.22)
Requires-Dist: matplotlib (>=3.4.0)
Requires-Dist: AllanTools (>=2019.9)
Requires-Dist: lmfit (>=1.1.0)
